agentos/__init__.py
agentos/agentos.py
agentos/py.typed
agentos/agent/__init__.py
agentos/agent/agent_executor.py
agentos/agent/agent_planner.py
agentos/agent/cli_agent.py
agentos/cli/__init__.py
agentos/cli/cli_cmd_basic.py
agentos/cli/cli_cmd_chat.py
agentos/cli/cli_cmd_schedule.py
agentos/cli/cli_cmd_setup.py
agentos/cli/cli_cmd_ui.py
agentos/cli/cli_cmd_utils.py
agentos/cli/cli_commands.py
agentos/cli/cli_helpers.py
agentos/cli/cli_parser.py
agentos/core/__init__.py
agentos/core/chat_history.py
agentos/core/config.py
agentos/core/docker_sandbox.py
agentos/core/isolate.py
agentos/core/path_resolver.py
agentos/core/process_manager.py
agentos/core/retry.py
agentos/core/scheduler.py
agentos/core/security.py
agentos/core/shutdown.py
agentos/core/threader.py
agentos/core/utils.py
agentos/database/__init__.py
agentos/database/db.py
agentos/database/db_agent_cli.py
agentos/database/db_agent_ops.py
agentos/database/db_agents.py
agentos/database/db_core.py
agentos/database/db_scheduler.py
agentos/llm/__init__.py
agentos/llm/answerer.py
agentos/llm/llm_providers.py
agentos/mcp/__init__.py
agentos/mcp/client.py
agentos/mcp/tools.py
agentos/static/styles.css
agentos/templates/agents.html
agentos/templates/base.html
agentos/templates/chat.html
agentos/templates/create_manifest.html
agentos/templates/dashboard.html
agentos/templates/run_agent.html
agentos/templates/schedule.html
agentos/web/__init__.py
agentos/web/web_routes.py
agentos/web/web_ui.py
agentos_ai-1.1.7.dist-info/LICENSE
agentos_ai-1.1.7.dist-info/METADATA
agentos_ai-1.1.7.dist-info/WHEEL
agentos_ai-1.1.7.dist-info/entry_points.txt
agentos_ai-1.1.7.dist-info/top_level.txt
agentos_ai-1.1.7.dist-info/RECORD
